ollama_easy_rag/__init__.py
ollama_easy_rag/ollama_easy_rag.py
ollama_easy_rag-0.0.4.dist-info/LICENSE
ollama_easy_rag-0.0.4.dist-info/METADATA
ollama_easy_rag-0.0.4.dist-info/WHEEL
ollama_easy_rag-0.0.4.dist-info/RECORD
