Metadata-Version: 2.3
Name: ollama-easy-rag
Version: 0.0.4
Summary: Simple and quick RAG (Retrieval Augmented Generation) using ollama API.
License: Apache-2.0
Keywords: ollama,langchain,ollama-easy-rag,easy rag,local rag
Author: Jayant Malik
Author-email: dev.jayantmalik@gmail.com
Requires-Python: >=3.9,<4.0
Classifier: License :: OSI Approved :: Apache Software License
Classifier: Programming Language :: Python :: 3
Classifier: Programming Language :: Python :: 3.9
Classifier: Programming Language :: Python :: 3.10
Classifier: Programming Language :: Python :: 3.11
Classifier: Programming Language :: Python :: 3.12
Classifier: Programming Language :: Python :: 3.13
Requires-Dist: lancedb (>=0.19.0,<0.20.0)
Requires-Dist: ollama (>=0.4.7,<0.5.0)
Requires-Dist: pyarrow (>=19.0.0,<20.0.0)
Project-URL: Changelog, https://github.com/developbharat/ollama-easy-rag
Project-URL: Documentation, https://github.com/developbharat/ollama-easy-rag
Project-URL: Homepage, https://github.com/developbharat/ollama-easy-rag
Project-URL: Repository, https://github.com/developbharat/ollama-easy-rag
